{
    "version": 1,
    "schedule": {
        "type": "simple",
        "interval": "1s"
    },
    "workflow": {
        "collect": {
            "metrics": {
                "/intel/linux/iface/<interface_name>/bytes_recv": {},
                "/intel/linux/iface/<interface_name>/bytes_sent": {},
                "/intel/linux/iface/<interface_name>/err_recv": {},
                "/intel/linux/iface/<interface_name>/fifo_recv": {}
            },
            "config": {
                "/intel/mock": {
                    "password": "secret",
                    "user": "root"
                }
            },
            "process": [
                {
                    "plugin_name": "passthru",
                    "process": null,
                    "publish": [
                        {
                            "plugin_name": "file",
                            "config": {
                                "file": "/tmp/published_interface"
                            }
                        }
                    ],
                    "config": null
                }
            ],
            "publish": null
        }
    }
}
